mlchemad/__init__.py
mlchemad/_data.py
mlchemad/applicability_domains.py
mlchemad/base.py
mlchemad/broccatelli2011.json
mlchemad/fisher1936.json
mlchemad/hemmerich2020.json
mlchemad/mekenyan1993.json
mlchemad/utils.py
mlchemad-1.5.2.dist-info/LICENSE
mlchemad-1.5.2.dist-info/METADATA
mlchemad-1.5.2.dist-info/WHEEL
mlchemad-1.5.2.dist-info/top_level.txt
mlchemad-1.5.2.dist-info/RECORD
