Metadata-Version: 2.1
Name: mlchemad
Version: 1.5.2
Summary: Applicability domains for cheminformactics.
Home-page: https://github.com/OlivierBeq/mlchemad
Author: Olivier J.M. Béquignon
Author-email: olivier.bequignon.maintainer@gmail.com
Maintainer: Olivier J.M. Béquignon
Maintainer-email: olivier.bequignon.maintainer@gmail.com
License: MIT
Keywords: applicability domain,cheminformatics,outlier molecule detection,out-of-distribution detection,machine learning
Classifier: Programming Language :: Python
Classifier: Programming Language :: Python :: 3
Classifier: Programming Language :: Python :: 3.11
Classifier: Programming Language :: Python :: 3.12
Classifier: Programming Language :: Python :: 3.9
Classifier: Programming Language :: Python :: 3.8
Classifier: Programming Language :: Python :: 3.7
Classifier: Programming Language :: Python :: 3.6
Classifier: License :: OSI Approved :: MIT License
Classifier: Operating System :: OS Independent
License-File: LICENSE
Requires-Dist: numpy
Requires-Dist: scipy
Requires-Dist: scikit-learn >1.2.2
Requires-Dist: pandas
